
  { "value" : "+json-seq",
    "concept" : "http:\/\/webconcepts.info\/concepts\/structured-syntax-suffix\/",
    "id" : "http:\/\/webconcepts.info\/concepts\/structured-syntax-suffix\/+json-seq",
    "details" : 
    [ 
      { "description" : "The use case for the \"+json-seq\" structured syntax suffix is the same as for \"+json\": It SHOULD be used by media types when parsing the JSON Text Sequence of a media type leads to a meaningful result, by simply using the generic JSON Text Sequence processing.",
        "documentation" : "http:\/\/tools.ietf.org\/html\/draft-wilde-json-seq-suffix#section-3",
        "specification" : "http:\/\/webconcepts.info\/specs\/IETF\/I-D\/wilde-json-seq-suffix",
        "spec-name" : "Internet Draft wilde-json-seq-suffix" } ] }