
  { "value" : "415",
    "concept" : "http:\/\/webconcepts.info\/concepts\/http-status-code\/",
    "id" : "http:\/\/webconcepts.info\/concepts\/http-status-code\/415",
    "description" : "Unsupported Media Type",
    "details" : 
    [ 
      { "description" : "The 415 (Unsupported Media Type) status code indicates that the origin server is refusing to service the request because the payload is in a format not supported by this method on the target resource. The format problem might be due to the request's indicated Content-Type or Content-Encoding, or as a result of inspecting the data directly.",
        "documentation" : "http:\/\/tools.ietf.org\/html\/rfc7231#section-6.5.13",
        "specification" : "http:\/\/webconcepts.info\/specs\/IETF\/RFC\/7231",
        "spec-name" : "RFC 7231" } ] }