
  { "value" : "intervalDisjoint",
    "concept" : "http:\/\/webconcepts.info\/concepts\/link-relation\/",
    "id" : "http:\/\/webconcepts.info\/concepts\/link-relation\/intervalDisjoint",
    "details" : 
    [ 
      { "description" : "Refers to a resource associated with a time interval that begins after the end of the time interval associated with the context resource, or ends before the beginning of the time interval associated with the context resource.",
        "documentation" : "http:\/\/www.w3.org\/TR\/owl-time\/#time:intervalDisjoint",
        "specification" : "http:\/\/webconcepts.info\/specs\/W3C\/TR\/owl-time",
        "spec-name" : "W3C TR http:\/\/www.w3.org\/TR\/owl-time" } ] }