
  { "value" : "Accept",
    "concept" : "http:\/\/webconcepts.info\/concepts\/http-header\/",
    "id" : "http:\/\/webconcepts.info\/concepts\/http-header\/Accept",
    "details" : 
    [ 
      { "description" : "The \"Accept\" header field can be used by user agents to specify response media types that are acceptable. Accept header fields can be used to indicate that the request is specifically limited to a small set of desired types, as in the case of a request for an in-line image.",
        "documentation" : "https:\/\/datatracker.ietf.org\/doc\/html\/rfc7231#section-5.3.2",
        "specification" : "http:\/\/webconcepts.info\/specs\/IETF\/RFC\/7231",
        "spec-name" : "RFC 7231" } ] }