
  { "value" : "EDIINT-Features",
    "concept" : "http:\/\/webconcepts.info\/concepts\/http-header\/",
    "id" : "http:\/\/webconcepts.info\/concepts\/http-header\/EDIINT-Features",
    "details" : 
    [ 
      { "description" : "The EDIINT-Features header field indicates the originating user agent is capable of supporting the features listed.",
        "documentation" : "http:\/\/tools.ietf.org\/html\/rfc6017#section-3",
        "specification" : "http:\/\/webconcepts.info\/specs\/IETF\/RFC\/6017",
        "spec-name" : "RFC 6017" } ] }